eyetools/__init__.py
eyetools/base.py
eyetools/cli.py
eyetools/mcp_server.py
eyetools/registry.py
eyetools/tool_manager.py
eyetools/utils.py
eyetools/core/__init__.py
eyetools/core/config_loader.py
eyetools/core/env_manager.py
eyetools/core/errors.py
eyetools/core/loader.py
eyetools/core/logging.py
eyetools/core/process_manager.py
eyetools/core/registry.py
eyetools/core/role_router.py
eyetools/core/tool_base.py
eyetools/core/tool_manager.py
eyetools/core/utils.py
eyetools/core/worker_entry.py
eyetools/core/worker_protocol.py
eyetools/tools/__init__.py
eyetools/tools/classification/__init__.py
eyetools/tools/classification/classification.py
eyetools-0.1.0.dist-info/METADATA
eyetools-0.1.0.dist-info/WHEEL
eyetools-0.1.0.dist-info/entry_points.txt
eyetools-0.1.0.dist-info/top_level.txt
eyetools-0.1.0.dist-info/RECORD
