Metadata-Version: 2.4
Name: eyetools
Version: 0.1.0
Summary: MCP tools server with auto-discovery and config support
Requires-Python: >=3.12
Requires-Dist: fastapi
Requires-Dist: uvicorn
Requires-Dist: pyyaml
Requires-Dist: mcp[cli]
Requires-Dist: pytest>=8.4.2
Requires-Dist: httpx>=0.28.1
Requires-Dist: fastmcp>=2.12.2
Requires-Dist: torch>=2.8.0
Requires-Dist: torchvision>=0.23.0
Requires-Dist: requests>=2.32.5
Requires-Dist: opencv-python>=4.12.0.88
Requires-Dist: matplotlib>=3.10.6
Requires-Dist: fire>=0.6.0
Requires-Dist: packaging>=21.0
Provides-Extra: dev
Requires-Dist: pytest; extra == "dev"
Requires-Dist: httpx; extra == "dev"
Requires-Dist: black; extra == "dev"
